phycat/PhycatClient.py
phycat/PhycatServer.py
phycat/PhycatSession.py
phycat/__init__.py
phycat/dummy.py
phycat/phycat_cli.py
phycat/phycat_make.py
phycat/configs/dummy.yml
phycat/configs/rpi4.yml
phycat/drivers/CuseTap.py
phycat/drivers/DeviceDriver.py
phycat/drivers/EmulatedMemory.py
phycat/drivers/I2cInterface.py
phycat/drivers/InterfaceDriver.py
phycat/drivers/PtyTap.py
phycat/drivers/UartInterface.py
phycat/drivers/__init__.py
phycat/helpers/__init__.py
phycat/helpers/driver_helper.py
phycat/helpers/format_helper.py
phycat/helpers/helper.py
phycat/helpers/log_helper.py
phycat/interfaces/Dummy.py
phycat/interfaces/Interface.py
phycat/interfaces/Serial.py
phycat/interfaces/__init__.py
phycat/interfaces/pigpio.py
phycat/protocol/__init__.py
phycat/protocol/phycatService.py
phycat/protocol/poly/.git
phycat/protocol/poly/can.yml
phycat/protocol/poly/device.yml
phycat/protocol/poly/gpio.yml
phycat/protocol/poly/i2c.yml
phycat/protocol/poly/phycat.yml
phycat/protocol/poly/spi.yml
phycat/protocol/poly/tim.yml
phycat/protocol/poly/uart.yml
phycat/templates/capabilities.c.j2
phycat/templates/capabilities.h.j2
phycat-0.0.11.dist-info/METADATA
phycat-0.0.11.dist-info/WHEEL
phycat-0.0.11.dist-info/entry_points.txt
phycat-0.0.11.dist-info/RECORD
