Metadata-Version: 2.4
Name: phycat
Version: 0.0.11
Summary: Phycat Tools and CLI
Project-URL: homepage, https://gitlab.com/phycat/phycat-py
Project-URL: repository, https://gitlab.com/phycat/phycat-py
Author-email: Jason Berger <berg472@gmail.com>
License: MIT
Requires-Python: >=3.7
Requires-Dist: cliify
Requires-Dist: cobs
Requires-Dist: jinja2
Requires-Dist: polypacket
Requires-Dist: prompt-toolkit
Requires-Dist: pyyaml
Requires-Dist: termcolor
